intronIC/classification/__init__.py
intronIC/classification/calibration_validator.py
intronIC/classification/classifier.py
intronIC/classification/clipping.py
intronIC/classification/fast_test_config.py
intronIC/classification/model_inspector.py
intronIC/classification/nested_cv.py
intronIC/classification/optimizer.py
intronIC/classification/predictor.py
intronIC/classification/progress_tracker.py
intronIC/classification/saturating.py
intronIC/classification/split_eval.py
intronIC/classification/trainer.py
intronIC/classification/transformers.py
intronIC/cli/__init__.py
intronIC/cli/args.py
intronIC/cli/args_old.py
intronIC/cli/colors.py
intronIC/cli/config.py
intronIC/cli/main.py
intronIC/cli/messenger.py
intronIC/cli/progress.py
intronIC/core/__init__.py
intronIC/core/intron.py
intronIC/core/models.py
intronIC/data/default_pretrained.model.pkl
intronIC/data/default_pretrained.model.sigmoid.pkl
intronIC/data/intronIC_scoring_PWMs.json
intronIC/data/u12_reference.introns.iic.gz
intronIC/data/u2_reference.introns.iic.gz
intronIC/data/test_data/Homo_sapiens.Chr19.Ensembl_91.fa.gz
intronIC/data/test_data/Homo_sapiens.Chr19.Ensembl_91.fa.gz.fxi
intronIC/data/test_data/Homo_sapiens.Chr19.Ensembl_91.gff3.gz
intronIC/extraction/__init__.py
intronIC/extraction/annotator.py
intronIC/extraction/boundary_correction.py
intronIC/extraction/filters.py
intronIC/extraction/intronator.py
intronIC/extraction/sequences.py
intronIC/file_io/__init__.py
intronIC/file_io/annotation_index.py
intronIC/file_io/annotation_store.py
intronIC/file_io/genome.py
intronIC/file_io/indexed_genome.py
intronIC/file_io/parsers.py
intronIC/file_io/sequence_store.py
intronIC/file_io/writers.py
intronIC/scoring/__init__.py
intronIC/scoring/branch_point.py
intronIC/scoring/margin_alignment.py
intronIC/scoring/normalizer.py
intronIC/scoring/prior_adjustment.py
intronIC/scoring/pwm.py
intronIC/scoring/scorer.py
intronIC/utils/__init__.py
intronIC/utils/config_loader.py
intronIC/utils/convert_pwm_format.py
intronic-2.1.0.dist-info/METADATA
intronic-2.1.0.dist-info/WHEEL
intronic-2.1.0.dist-info/entry_points.txt
intronic-2.1.0.dist-info/licenses/LICENSE
intronic-2.1.0.dist-info/RECORD
