Metadata-Version: 2.4
Name: intronIC
Version: 2.1.0
Summary: Intron classification tool for identifying U2-type and U12-type introns using SVM
Project-URL: Homepage, https://github.com/glarue/intronIC
Project-URL: Repository, https://github.com/glarue/intronIC
Project-URL: Issues, https://github.com/glarue/intronIC/issues
Author-email: "Graham E. Larue" <egrahamlarue@gmail.com>
License: GPL-3.0
License-File: LICENSE
Classifier: Development Status :: 5 - Production/Stable
Classifier: Intended Audience :: Science/Research
Classifier: License :: OSI Approved :: GNU General Public License v3 (GPLv3)
Classifier: Programming Language :: Python :: 3
Classifier: Programming Language :: Python :: 3.10
Classifier: Programming Language :: Python :: 3.11
Classifier: Programming Language :: Python :: 3.12
Classifier: Topic :: Scientific/Engineering :: Bio-Informatics
Requires-Python: >=3.10
Requires-Dist: biogl>=3.0.1
Requires-Dist: joblib>=1.0.0
Requires-Dist: matplotlib>=3.3.0
Requires-Dist: networkx>=2.5.1
Requires-Dist: numpy>=1.19.0
Requires-Dist: pyfastx>=0.8.0
Requires-Dist: pyyaml>=5.0
Requires-Dist: rich>=10.0
Requires-Dist: scikit-learn<2.0,>=0.22
Requires-Dist: scipy>=1.5.0
Requires-Dist: smart-open>=5.0.0
Requires-Dist: tqdm>=4.0.0
Provides-Extra: dev
Requires-Dist: black>=22.0; extra == 'dev'
Requires-Dist: ipython>=7.0; extra == 'dev'
Requires-Dist: mypy>=0.990; extra == 'dev'
Requires-Dist: pytest-cov>=3.0; extra == 'dev'
Requires-Dist: pytest>=7.0; extra == 'dev'
Requires-Dist: ruff>=0.1.0; extra == 'dev'
Provides-Extra: test
Requires-Dist: pytest-cov>=3.0; extra == 'test'
Requires-Dist: pytest>=7.0; extra == 'test'
